Metadata-Version: 2.4
Name: ca-ua-image_processing
Version: 0.0.1
Summary: Image processing package using skimage
Home-page: https://github.com/Ca-ua/image-processing-package
Author: Caua
Requires-Python: >=3.8
Dynamic: author
Dynamic: description
Dynamic: description-content-type
Dynamic: home-page
Dynamic: requires-python
Dynamic: summary
